pwploads/__init__.py
pwploads/collapse_calcs.py
pwploads/connections.py
pwploads/design_factors.py
pwploads/inputs.py
pwploads/load_cases.py
pwploads/plot.py
pwploads/prepare_cases.py
pwploads/unit_converter.py
pwploads/utilities.py
pwploads/von_mises.py
pwploads/axial/__init__.py
pwploads/axial/cases.py
pwploads/axial/forces.py
pwploads/axial/main.py
pwploads/burst/__init__.py
pwploads/burst/cases.py
pwploads/burst/main.py
pwploads/burst/pressure_external.py
pwploads/burst/pressure_internal.py
pwploads/collapse/__init__.py
pwploads/collapse/cases.py
pwploads/collapse/main.py
pwploads/collapse/pressure_external.py
pwploads/collapse/pressure_internal.py
pwploads-0.4.1.dist-info/LICENSE
pwploads-0.4.1.dist-info/METADATA
pwploads-0.4.1.dist-info/WHEEL
pwploads-0.4.1.dist-info/top_level.txt
pwploads-0.4.1.dist-info/RECORD
